pymbd/__init__.py
pymbd/fortran.py
pymbd/pymbd.py
pymbd/tensorflow.py
pymbd/utils.py
pymbd/vdw-params.csv
src/mbd.h
pymbd/_libmbd.abi3.so
pymbd-0.9.2.dist-info/LICENSE
pymbd-0.9.2.dist-info/WHEEL
pymbd-0.9.2.dist-info/METADATA
pymbd-0.9.2.dist-info/RECORD
