Metadata-Version: 2.1
Name: pymbd
Version: 0.9.2
Summary: Many-body dispersion library
Home-page: https://github.com/jhrmnn/libmbd
License: MPL-2.0
Author: Jan Hermann
Author-email: dev@jan.hermann.name
Requires-Python: >=3.5,<4.0
Classifier: Development Status :: 4 - Beta
Classifier: Environment :: Console
Classifier: Intended Audience :: Science/Research
Classifier: License :: OSI Approved
Classifier: Operating System :: MacOS :: MacOS X
Classifier: Operating System :: POSIX :: Linux
Classifier: Programming Language :: Fortran
Classifier: Programming Language :: Python :: 3
Classifier: Programming Language :: Python :: 3.5
Classifier: Programming Language :: Python :: 3.6
Classifier: Programming Language :: Python :: 3.7
Classifier: Programming Language :: Python :: 3.8
Classifier: Topic :: Scientific/Engineering :: Chemistry
Classifier: Topic :: Scientific/Engineering :: Physics
Provides-Extra: mpi
Provides-Extra: test
Requires-Dist: mpi4py (>=3,<4); extra == "mpi"
Requires-Dist: numpy (>=1,<2)
Requires-Dist: pytest (>=5,<6); extra == "test"
Requires-Dist: scipy (>=1,<2)
Project-URL: Documentation, https://jhrmnn.github.io/libmbd/pymbd
Project-URL: Repository, https://github.com/jhrmnn/libmbd
